conanex/__init__.py
conanex/cli.py
conanex/main.py
conanex/types.py
conanex-2.3.0.dist-info/LICENSE
conanex-2.3.0.dist-info/METADATA
conanex-2.3.0.dist-info/WHEEL
conanex-2.3.0.dist-info/entry_points.txt
conanex-2.3.0.dist-info/top_level.txt
conanex-2.3.0.dist-info/RECORD
