Metadata-Version: 2.1
Name: conanex
Version: 2.3.0
Summary: Conan Extended C/C++ package manager
Home-page: https://github.com/redradist/conanex
Author: redradist
Author-email: redradist@gmail.com
License: MIT
Keywords: C/C++,package,libraries,developer,manager,dependency,tool,c,c++,cpp
Classifier: Development Status :: 5 - Production/Stable
Classifier: Intended Audience :: Developers
Classifier: Topic :: Software Development :: Build Tools
Classifier: License :: OSI Approved :: MIT License
Classifier: Programming Language :: Python :: 3
Classifier: Programming Language :: Python :: 3.6
Classifier: Programming Language :: Python :: 3.7
Classifier: Programming Language :: Python :: 3.8
Classifier: Programming Language :: Python :: 3.9
Classifier: Programming Language :: Python :: 3.10
Classifier: Programming Language :: Python :: 3.11
Classifier: Programming Language :: Python :: 3.12
Classifier: Programming Language :: Python :: 3.13
License-File: LICENSE
Requires-Dist: conan>=2.0.14
